mobi/__init__.py
mobi/apns/__init__.py
mobi/apns/client.py
mobi/apns/exceptions.py
mobi/apns/utils.py
mobi_apns-0.2.9.dist-info/LICENSE.txt
mobi_apns-0.2.9.dist-info/METADATA
mobi_apns-0.2.9.dist-info/RECORD
mobi_apns-0.2.9.dist-info/WHEEL
mobi_apns-0.2.9.dist-info/top_level.txt
