Metadata-Version: 2.1
Name: mobi-apns
Version: 0.2.9
Summary: A library for interacting with APNs using HTTP/2 and token-based authentication.
Home-page: https://bitbucket.org/mobivention/mobi-apns/
Author: Sören Busch, Gene Sluder
Author-email: sbusch@mobivention.com
License: MIT license
Download-URL: https://bitbucket.org/mobivention/mobi-apns/get/0.2.9.zip
Project-URL: Bug Reports, https://bitbucket.org/mobivention/mobi-apns/issues
Project-URL: Source, https://bitbucket.org/mobivention/mobi-apns/
Project-URL: Company Home, https://www.mobivention.com
Keywords: apns,push notifications
Platform: UNKNOWN
Requires-Python: >=3.5
Requires-Dist: cryptography
Requires-Dist: hyper
Requires-Dist: pyjwt
